{
    "success": true,
    "result":{
        "products": [
            {
                "id":0,
                "code": "34534345",
                "avail": true,
                "name": "1Canon PowerShot SX400 IS с улучшенной матрицей и объективом",
                "props":[
                    {"name":"Физический размер 23.2 x 15.2 мм"},
                    {"name":"Диафрагма CMOS"},
                    {"name":"Формат записи RAW, JPEG, MP4 и другие"},
                    {"name":"Фокусное расстояние 18-55 мм."}
                ]
            },
            {
                "id":2,
                "code": "34534345",
                "avail": true,
                "name": "2Canon PowerShot SX400 IS с улучшенной матрицей и объективом",
                "props":[
                    {"name":"1Физический размер 23.2 x 15.2 мм"},
                    {"name":"2Диафрагма CMOS"},
                    {"name":"3Формат записи RAW, JPEG, MP4 и другие"},
                    {"name":"4Фокусное расстояние 18-55 мм."}
                ]
            }
        ]
    }
}